notifykit-0.0.7.dist-info/METADATA
notifykit-0.0.7.dist-info/WHEEL
notifykit-0.0.7.dist-info/license_files/LICENSE
notifykit/_notifier.py
notifykit/_notifykit_lib.pyi
notifykit/__init__.py
notifykit/_testing.py
notifykit/py.typed
notifykit/_notifykit_lib.abi3.so
notifykit-0.0.7.dist-info/RECORD
