Metadata-Version: 2.1
Name: notifykit
Version: 0.0.7
Classifier: Programming Language :: Rust
Classifier: Programming Language :: Python :: Implementation :: CPython
Classifier: Programming Language :: Python :: Implementation :: PyPy
Requires-Dist: anyio >=3.0.0
License-File: LICENSE
Summary: A modern efficient Python toolkit for building applications that need to watch filesystem changes
Home-Page: https://github.com/roma-glushko/notifykit
Author-email: Roman Glushko <roman.glushko.m@gmail.com>
License: Apache 2.0
Requires-Python: >=3.8
Project-URL: Homepage, https://github.com/roma-glushko/notifykit
